{"assets/cards/artifact_crystal.yaml":["assets/cards/artifact_crystal.yaml"],"assets/cards/domain_library.yaml":["assets/cards/domain_library.yaml"],"assets/cards/index.yaml":["assets/cards/index.yaml"],"assets/cards/monster_basic.yaml":["assets/cards/monster_basic.yaml"],"assets/cards/simple_draw.yaml":["assets/cards/simple_draw.yaml"],"assets/cards/spl_typhoon.yaml":["assets/cards/spl_typhoon.yaml"],"assets/cards/spl_x07.yaml":["assets/cards/spl_x07.yaml"],"assets/cards/van001.yaml":["assets/cards/van001.yaml"],"assets/cards/van_art.yaml":["assets/cards/van_art.yaml"],"assets/cards/van_domain.yaml":["assets/cards/van_domain.yaml"]}